easybill_rest/__init__.py
easybill_rest/helper.py
easybill_rest/resources/resource_abstract.py
easybill_rest/resources/resource_attachments.py
easybill_rest/resources/resource_contacts.py
easybill_rest/resources/resource_customer_groups.py
easybill_rest/resources/resource_customers.py
easybill_rest/resources/resource_discount_position_groups.py
easybill_rest/resources/resource_discount_positions.py
easybill_rest/resources/resource_document_payments.py
easybill_rest/resources/resource_document_versions.py
easybill_rest/resources/resource_documents.py
easybill_rest/resources/resource_logins.py
easybill_rest/resources/resource_pdf_templates.py
easybill_rest/resources/resource_position_groups.py
easybill_rest/resources/resource_positions.py
easybill_rest/resources/resource_post_boxes.py
easybill_rest/resources/resource_projects.py
easybill_rest/resources/resource_sepa_payments.py
easybill_rest/resources/resource_serial_numbers.py
easybill_rest/resources/resource_stocks.py
easybill_rest/resources/resource_tasks.py
easybill_rest/resources/resource_text_templates.py
easybill_rest/resources/resource_time_trackings.py
easybill_rest/resources/resource_webhooks.py
easybill_rest/tests/suite_unit.py
easybill_rest/tests/test_abstract_resource.py
easybill_rest/tests/test_attachments.py
easybill_rest/tests/test_case_abstract.py
easybill_rest/tests/test_client.py
easybill_rest/tests/test_contacts.py
easybill_rest/tests/test_customer_groups.py
easybill_rest/tests/test_customers.py
easybill_rest/tests/test_discount_position_groups.py
easybill_rest/tests/test_discount_positions.py
easybill_rest/tests/test_document_payments.py
easybill_rest/tests/test_document_versions.py
easybill_rest/tests/test_documents.py
easybill_rest/tests/test_helper.py
easybill_rest/tests/test_logins.py
easybill_rest/tests/test_pdf_templates.py
easybill_rest/tests/test_position_groups.py
easybill_rest/tests/test_positions.py
easybill_rest/tests/test_post_boxes.py
easybill_rest/tests/test_projects.py
easybill_rest-0.6.0.dist-info/METADATA
easybill_rest-0.6.0.dist-info/WHEEL
easybill_rest-0.6.0.dist-info/RECORD
