Metadata-Version: 2.1
Name: easybill-rest
Version: 0.6.0
Summary: easybill_rest is a library to work with the easybill REST API (https://www.easybill.de/api/)
License: MIT
Author: Jan Nöhles
Author-email: jan.noehles@easybill.de
Requires-Python: >=3.11,<4.0
Classifier: License :: OSI Approved :: MIT License
Classifier: Programming Language :: Python :: 3
Classifier: Programming Language :: Python :: 3.11
Classifier: Programming Language :: Python :: 3.12
Requires-Dist: httpx (>=0.27.2,<0.28.0)
